AmericaChannel/__init__.py
AmericaChannel/audio/__init__.py
AmericaChannel/video/__init__.py
test/__init__.py
AmericaChannel-2023.9.1.dist-info/LICENSE.txt
AmericaChannel-2023.9.1.dist-info/METADATA
AmericaChannel-2023.9.1.dist-info/WHEEL
AmericaChannel-2023.9.1.dist-info/top_level.txt
AmericaChannel-2023.9.1.dist-info/RECORD
